healthybreakfast/__init__.py
healthybreakfast/find/Deficiency.py
healthybreakfast/find/Rec.py
healthybreakfast/find/Recommend.py
healthybreakfast/find/__init__.py
healthybreakfast/manual/Cereals.py
healthybreakfast/manual/Cereals1.py
healthybreakfast/manual/Person.py
healthybreakfast/manual/__init__.py
healthybreakfast-0.7.dist-info/METADATA
healthybreakfast-0.7.dist-info/WHEEL
healthybreakfast-0.7.dist-info/top_level.txt
healthybreakfast-0.7.dist-info/RECORD
