Metadata-Version: 2.1
Name: healthybreakfast
Version: 0.7
Summary: Eat healthy stay healthy
Home-page: https://github.com/Sowmya-Chenthi-Kumar/DATA533_LAB4
Author: Sowmya and Yatin
Author-email: yatin.behl@gmail.com
License: MIT
Platform: UNKNOWN
